{
    "os": "Linux-6.1.38-59.109.amzn2023.x86_64-x86_64-with-glibc2.34",
    "python": "3.9.10",
    "heartbeatAt": "2023-11-19T05:34:36.458849",
    "startedAt": "2023-11-19T05:34:36.053225",
    "docker": null,
    "cuda": null,
    "args": [],
    "state": "running",
    "program": "/home/ec2-user/cortex.t/neurons/test_images.py",
    "codePathLocal": "test_images.py",
    "codePath": "neurons/test_images.py",
    "git": {
        "remote": "https://github.com/BitAPAI/cortex.t",
        "commit": "5e2125428f566ea84cfaeb44595343ed915dc765"
    },
    "email": "surcyf@gmail.com",
    "root": "/home/ec2-user/cortex.t",
    "host": "ip-172-31-46-82.ca-central-1.compute.internal",
    "username": "ec2-user",
    "executable": "/home/ec2-user/anaconda3/envs/bit2/bin/python3",
    "cpu_count": 16,
    "cpu_count_logical": 32,
    "cpu_freq": {
        "current": 3500.1921875000003,
        "min": 0.0,
        "max": 0.0
    },
    "cpu_freq_per_core": [
        {
            "current": 3501.039,
            "min": 0.0,
            "max": 0.0
        },
        {
            "current": 3500.02,
            "min": 0.0,
            "max": 0.0
        },
        {
            "current": 3499.063,
            "min": 0.0,
            "max": 0.0
        },
        {
            "current": 3499.939,
            "min": 0.0,
            "max": 0.0
        },
        {
            "current": 3499.439,
            "min": 0.0,
            "max": 0.0
        },
        {
            "current": 3498.709,
            "min": 0.0,
            "max": 0.0
        },
        {
            "current": 3499.824,
            "min": 0.0,
            "max": 0.0
        },
        {
            "current": 3501.03,
            "min": 0.0,
            "max": 0.0
        },
        {
            "current": 3499.909,
            "min": 0.0,
            "max": 0.0
        },
        {
            "current": 3500.53,
            "min": 0.0,
            "max": 0.0
        },
        {
            "current": 3502.809,
            "min": 0.0,
            "max": 0.0
        },
        {
            "current": 3500.26,
            "min": 0.0,
            "max": 0.0
        },
        {
            "current": 3499.897,
            "min": 0.0,
            "max": 0.0
        },
        {
            "current": 3499.978,
            "min": 0.0,
            "max": 0.0
        },
        {
            "current": 3499.897,
            "min": 0.0,
            "max": 0.0
        },
        {
            "current": 3499.964,
            "min": 0.0,
            "max": 0.0
        },
        {
            "current": 3499.995,
            "min": 0.0,
            "max": 0.0
        },
        {
            "current": 3500.768,
            "min": 0.0,
            "max": 0.0
        },
        {
            "current": 3499.983,
            "min": 0.0,
            "max": 0.0
        },
        {
            "current": 3499.9,
            "min": 0.0,
            "max": 0.0
        },
        {
            "current": 3498.846,
            "min": 0.0,
            "max": 0.0
        },
        {
            "current": 3500.547,
            "min": 0.0,
            "max": 0.0
        },
        {
            "current": 3500.22,
            "min": 0.0,
            "max": 0.0
        },
        {
            "current": 3500.208,
            "min": 0.0,
            "max": 0.0
        },
        {
            "current": 3499.506,
            "min": 0.0,
            "max": 0.0
        },
        {
            "current": 3501.044,
            "min": 0.0,
            "max": 0.0
        },
        {
            "current": 3500.704,
            "min": 0.0,
            "max": 0.0
        },
        {
            "current": 3500.466,
            "min": 0.0,
            "max": 0.0
        },
        {
            "current": 3499.662,
            "min": 0.0,
            "max": 0.0
        },
        {
            "current": 3501.516,
            "min": 0.0,
            "max": 0.0
        },
        {
            "current": 3500.625,
            "min": 0.0,
            "max": 0.0
        },
        {
            "current": 3499.853,
            "min": 0.0,
            "max": 0.0
        }
    ],
    "disk": {
        "/": {
            "total": 499.9257621765137,
            "used": 212.93287658691406
        }
    },
    "memory": {
        "total": 247.71762084960938
    }
}
